{".class": "MypyFile", "_fullname": "google.ads.google_ads.v2.proto.errors.date_error_pb2", "is_partial_stub_package": false, "is_stub": true, "names": {".class": "SymbolTable", "DateErrorEnum": {".class": "SymbolTableNode", "kind": "Gdef", "node": {".class": "TypeInfo", "_promote": null, "abstract_attributes": [], "bases": ["google.protobuf.message.Message"], "declared_metaclass": null, "defn": {".class": "ClassDef", "fullname": "google.ads.google_ads.v2.proto.errors.date_error_pb2.DateErrorEnum", "name": "DateErrorEnum", "type_vars": []}, "flags": [], "fullname": "google.ads.google_ads.v2.proto.errors.date_error_pb2.DateErrorEnum", "metaclass_type": null, "metadata": {}, "module_name": "google.ads.google_ads.v2.proto.errors.date_error_pb2", "mro": ["google.ads.google_ads.v2.proto.errors.date_error_pb2.DateErrorEnum", "google.protobuf.message.Message", "builtins.object"], "names": {".class": "SymbolTable", "CopyFrom": {".class": "SymbolTableNode", "kind": "Mdef", "node": {".class": "FuncDef", "arg_kinds": [0, 0], "arg_names": ["self", "other_msg"], "flags": [], "fullname": "google.ads.google_ads.v2.proto.errors.date_error_pb2.DateErrorEnum.CopyFrom", "name": "CopyFrom", "type": {".class": "CallableType", "arg_kinds": [0, 0], "arg_names": ["self", "other_msg"], "arg_types": ["google.ads.google_ads.v2.proto.errors.date_error_pb2.DateErrorEnum", "google.protobuf.message.Message"], "bound_args": [], "def_extras": {"first_arg": "self"}, "fallback": "builtins.function", "implicit": false, "is_ellipsis_args": false, "name": "CopyFrom of DateErrorEnum", "ret_type": {".class": "NoneType"}, "variables": []}}}, "DATE_RANGE_MINIMUM_AND_MAXIMUM_DATES_BOTH_NULL": {".class": "SymbolTableNode", "kind": "Mdef", "node": {".class": "Var", "flags": ["is_initialized_in_class", "is_ready"], "fullname": "google.ads.google_ads.v2.proto.errors.date_error_pb2.DateErrorEnum.DATE_RANGE_MINIMUM_AND_MAXIMUM_DATES_BOTH_NULL", "name": "DATE_RANGE_MINIMUM_AND_MAXIMUM_DATES_BOTH_NULL", "type": {".class": "LiteralType", "fallback": "builtins.int", "value": 10}}}, "DATE_RANGE_MINIMUM_DATE_LATER_THAN_MAXIMUM_DATE": {".class": "SymbolTableNode", "kind": "Mdef", "node": {".class": "Var", "flags": ["is_initialized_in_class", "is_ready"], "fullname": "google.ads.google_ads.v2.proto.errors.date_error_pb2.DateErrorEnum.DATE_RANGE_MINIMUM_DATE_LATER_THAN_MAXIMUM_DATE", "name": "DATE_RANGE_MINIMUM_DATE_LATER_THAN_MAXIMUM_DATE", "type": {".class": "LiteralType", "fallback": "builtins.int", "value": 9}}}, "DateError": {".class": "SymbolTableNode", "kind": "Mdef", "node": {".class": "TypeInfo", "_promote": null, "abstract_attributes": [], "bases": ["builtins.object"], "declared_metaclass": null, "defn": {".class": "ClassDef", "fullname": "google.ads.google_ads.v2.proto.errors.date_error_pb2.DateErrorEnum.DateError", "name": "DateError", "type_vars": []}, "flags": [], "fullname": "google.ads.google_ads.v2.proto.errors.date_error_pb2.DateErrorEnum.DateError", "metaclass_type": null, "metadata": {}, "module_name": "google.ads.google_ads.v2.proto.errors.date_error_pb2", "mro": ["google.ads.google_ads.v2.proto.errors.date_error_pb2.DateErrorEnum.DateError", "builtins.object"], "names": {".class": "SymbolTable", "ClosedKeyType": {".class": "SymbolTableNode", "kind": "Mdef", "node": {".class": "TypeAlias", "alias_tvars": [], "column": 8, "fullname": "google.ads.google_ads.v2.proto.errors.date_error_pb2.DateErrorEnum.DateError.ClosedKeyType", "line": 24, "no_args": false, "normalized": false, "target": {".class": "UnionType", "items": [{".class": "LiteralType", "fallback": "builtins.str", "value": "UNSPECIFIED"}, {".class": "LiteralType", "fallback": "builtins.str", "value": "UNKNOWN"}, {".class": "LiteralType", "fallback": "builtins.str", "value": "INVALID_FIELD_VALUES_IN_DATE"}, {".class": "LiteralType", "fallback": "builtins.str", "value": "INVALID_FIELD_VALUES_IN_DATE_TIME"}, {".class": "LiteralType", "fallback": "builtins.str", "value": "INVALID_STRING_DATE"}, {".class": "LiteralType", "fallback": "builtins.str", "value": "INVALID_STRING_DATE_TIME_MICROS"}, {".class": "LiteralType", "fallback": "builtins.str", "value": "INVALID_STRING_DATE_TIME_SECONDS"}, {".class": "LiteralType", "fallback": "builtins.str", "value": "INVALID_STRING_DATE_TIME_SECONDS_WITH_OFFSET"}, {".class": "LiteralType", "fallback": "builtins.str", "value": "EARLIER_THAN_MINIMUM_DATE"}, {".class": "LiteralType", "fallback": "builtins.str", "value": "LATER_THAN_MAXIMUM_DATE"}, {".class": "LiteralType", "fallback": "builtins.str", "value": "DATE_RANGE_MINIMUM_DATE_LATER_THAN_MAXIMUM_DATE"}, {".class": "LiteralType", "fallback": "builtins.str", "value": "DATE_RANGE_MINIMUM_AND_MAXIMUM_DATES_BOTH_NULL"}]}}}, "ClosedValueType": {".class": "SymbolTableNode", "kind": "Mdef", "node": {".class": "TypeAlias", "alias_tvars": [], "column": 8, "fullname": "google.ads.google_ads.v2.proto.errors.date_error_pb2.DateErrorEnum.DateError.ClosedValueType", "line": 25, "no_args": false, "normalized": false, "target": {".class": "UnionType", "items": [{".class": "LiteralType", "fallback": "builtins.int", "value": 0}, {".class": "LiteralType", "fallback": "builtins.int", "value": 1}, {".class": "LiteralType", "fallback": "builtins.int", "value": 2}, {".class": "LiteralType", "fallback": "builtins.int", "value": 3}, {".class": "LiteralType", "fallback": "builtins.int", "value": 4}, {".class": "LiteralType", "fallback": "builtins.int", "value": 6}, {".class": "LiteralType", "fallback": "builtins.int", "value": 11}, {".class": "LiteralType", "fallback": "builtins.int", "value": 12}, {".class": "LiteralType", "fallback": "builtins.int", "value": 7}, {".class": "LiteralType", "fallback": "builtins.int", "value": 8}, {".class": "LiteralType", "fallback": "builtins.int", "value": 9}, {".class": "LiteralType", "fallback": "builtins.int", "value": 10}]}}}, "DATE_RANGE_MINIMUM_AND_MAXIMUM_DATES_BOTH_NULL": {".class": "SymbolTableNode", "kind": "Mdef", "node": {".class": "Var", "flags": ["is_initialized_in_class", "is_ready"], "fullname": "google.ads.google_ads.v2.proto.errors.date_error_pb2.DateErrorEnum.DateError.DATE_RANGE_MINIMUM_AND_MAXIMUM_DATES_BOTH_NULL", "name": "DATE_RANGE_MINIMUM_AND_MAXIMUM_DATES_BOTH_NULL", "type": {".class": "LiteralType", "fallback": "builtins.int", "value": 10}}}, "DATE_RANGE_MINIMUM_DATE_LATER_THAN_MAXIMUM_DATE": {".class": "SymbolTableNode", "kind": "Mdef", "node": {".class": "Var", "flags": ["is_initialized_in_class", "is_ready"], "fullname": "google.ads.google_ads.v2.proto.errors.date_error_pb2.DateErrorEnum.DateError.DATE_RANGE_MINIMUM_DATE_LATER_THAN_MAXIMUM_DATE", "name": "DATE_RANGE_MINIMUM_DATE_LATER_THAN_MAXIMUM_DATE", "type": {".class": "LiteralType", "fallback": "builtins.int", "value": 9}}}, "DESCRIPTOR": {".class": "SymbolTableNode", "kind": "Mdef", "node": {".class": "Var", "flags": ["is_initialized_in_class", "is_ready"], "fullname": "google.ads.google_ads.v2.proto.errors.date_error_pb2.DateErrorEnum.DateError.DESCRIPTOR", "name": "DESCRIPTOR", "type": "google.protobuf.descriptor.EnumDescriptor"}}, "EARLIER_THAN_MINIMUM_DATE": {".class": "SymbolTableNode", "kind": "Mdef", "node": {".class": "Var", "flags": ["is_initialized_in_class", "is_ready"], "fullname": "google.ads.google_ads.v2.proto.errors.date_error_pb2.DateErrorEnum.DateError.EARLIER_THAN_MINIMUM_DATE", "name": "EARLIER_THAN_MINIMUM_DATE", "type": {".class": "LiteralType", "fallback": "builtins.int", "value": 7}}}, "INVALID_FIELD_VALUES_IN_DATE": {".class": "SymbolTableNode", "kind": "Mdef", "node": {".class": "Var", "flags": ["is_initialized_in_class", "is_ready"], "fullname": "google.ads.google_ads.v2.proto.errors.date_error_pb2.DateErrorEnum.DateError.INVALID_FIELD_VALUES_IN_DATE", "name": "INVALID_FIELD_VALUES_IN_DATE", "type": {".class": "LiteralType", "fallback": "builtins.int", "value": 2}}}, "INVALID_FIELD_VALUES_IN_DATE_TIME": {".class": "SymbolTableNode", "kind": "Mdef", "node": {".class": "Var", "flags": ["is_initialized_in_class", "is_ready"], "fullname": "google.ads.google_ads.v2.proto.errors.date_error_pb2.DateErrorEnum.DateError.INVALID_FIELD_VALUES_IN_DATE_TIME", "name": "INVALID_FIELD_VALUES_IN_DATE_TIME", "type": {".class": "LiteralType", "fallback": "builtins.int", "value": 3}}}, "INVALID_STRING_DATE": {".class": "SymbolTableNode", "kind": "Mdef", "node": {".class": "Var", "flags": ["is_initialized_in_class", "is_ready"], "fullname": "google.ads.google_ads.v2.proto.errors.date_error_pb2.DateErrorEnum.DateError.INVALID_STRING_DATE", "name": "INVALID_STRING_DATE", "type": {".class": "LiteralType", "fallback": "builtins.int", "value": 4}}}, "INVALID_STRING_DATE_TIME_MICROS": {".class": "SymbolTableNode", "kind": "Mdef", "node": {".class": "Var", "flags": ["is_initialized_in_class", "is_ready"], "fullname": "google.ads.google_ads.v2.proto.errors.date_error_pb2.DateErrorEnum.DateError.INVALID_STRING_DATE_TIME_MICROS", "name": "INVALID_STRING_DATE_TIME_MICROS", "type": {".class": "LiteralType", "fallback": "builtins.int", "value": 6}}}, "INVALID_STRING_DATE_TIME_SECONDS": {".class": "SymbolTableNode", "kind": "Mdef", "node": {".class": "Var", "flags": ["is_initialized_in_class", "is_ready"], "fullname": "google.ads.google_ads.v2.proto.errors.date_error_pb2.DateErrorEnum.DateError.INVALID_STRING_DATE_TIME_SECONDS", "name": "INVALID_STRING_DATE_TIME_SECONDS", "type": {".class": "LiteralType", "fallback": "builtins.int", "value": 11}}}, "INVALID_STRING_DATE_TIME_SECONDS_WITH_OFFSET": {".class": "SymbolTableNode", "kind": "Mdef", "node": {".class": "Var", "flags": ["is_initialized_in_class", "is_ready"], "fullname": "google.ads.google_ads.v2.proto.errors.date_error_pb2.DateErrorEnum.DateError.INVALID_STRING_DATE_TIME_SECONDS_WITH_OFFSET", "name": "INVALID_STRING_DATE_TIME_SECONDS_WITH_OFFSET", "type": {".class": "LiteralType", "fallback": "builtins.int", "value": 12}}}, "LATER_THAN_MAXIMUM_DATE": {".class": "SymbolTableNode", "kind": "Mdef", "node": {".class": "Var", "flags": ["is_initialized_in_class", "is_ready"], "fullname": "google.ads.google_ads.v2.proto.errors.date_error_pb2.DateErrorEnum.DateError.LATER_THAN_MAXIMUM_DATE", "name": "LATER_THAN_MAXIMUM_DATE", "type": {".class": "LiteralType", "fallback": "builtins.int", "value": 8}}}, "Name": {".class": "SymbolTableNode", "kind": "Mdef", "node": {".class": "Decorator", "func": {".class": "FuncDef", "arg_kinds": [0, 0], "arg_names": ["cls", "number"], "flags": ["is_class", "is_decorated"], "fullname": "google.ads.google_ads.v2.proto.errors.date_error_pb2.DateErrorEnum.DateError.Name", "name": "Name", "type": {".class": "CallableType", "arg_kinds": [0, 0], "arg_names": ["cls", "number"], "arg_types": [{".class": "TypeType", "item": "google.ads.google_ads.v2.proto.errors.date_error_pb2.DateErrorEnum.DateError"}, {".class": "UnionType", "items": [{".class": "LiteralType", "fallback": "builtins.int", "value": 0}, {".class": "LiteralType", "fallback": "builtins.int", "value": 1}, {".class": "LiteralType", "fallback": "builtins.int", "value": 2}, {".class": "LiteralType", "fallback": "builtins.int", "value": 3}, {".class": "LiteralType", "fallback": "builtins.int", "value": 4}, {".class": "LiteralType", "fallback": "builtins.int", "value": 6}, {".class": "LiteralType", "fallback": "builtins.int", "value": 11}, {".class": "LiteralType", "fallback": "builtins.int", "value": 12}, {".class": "LiteralType", "fallback": "builtins.int", "value": 7}, {".class": "LiteralType", "fallback": "builtins.int", "value": 8}, {".class": "LiteralType", "fallback": "builtins.int", "value": 9}, {".class": "LiteralType", "fallback": "builtins.int", "value": 10}]}], "bound_args": [], "def_extras": {"first_arg": "cls"}, "fallback": "builtins.function", "implicit": false, "is_ellipsis_args": false, "name": "Name of DateError", "ret_type": "builtins.str", "variables": []}}, "is_overload": false, "var": {".class": "Var", "flags": ["is_initialized_in_class", "is_classmethod", "is_ready"], "fullname": null, "name": "Name", "type": {".class": "CallableType", "arg_kinds": [0, 0], "arg_names": ["cls", "number"], "arg_types": [{".class": "TypeType", "item": "google.ads.google_ads.v2.proto.errors.date_error_pb2.DateErrorEnum.DateError"}, {".class": "UnionType", "items": [{".class": "LiteralType", "fallback": "builtins.int", "value": 0}, {".class": "LiteralType", "fallback": "builtins.int", "value": 1}, {".class": "LiteralType", "fallback": "builtins.int", "value": 2}, {".class": "LiteralType", "fallback": "builtins.int", "value": 3}, {".class": "LiteralType", "fallback": "builtins.int", "value": 4}, {".class": "LiteralType", "fallback": "builtins.int", "value": 6}, {".class": "LiteralType", "fallback": "builtins.int", "value": 11}, {".class": "LiteralType", "fallback": "builtins.int", "value": 12}, {".class": "LiteralType", "fallback": "builtins.int", "value": 7}, {".class": "LiteralType", "fallback": "builtins.int", "value": 8}, {".class": "LiteralType", "fallback": "builtins.int", "value": 9}, {".class": "LiteralType", "fallback": "builtins.int", "value": 10}]}], "bound_args": [], "def_extras": {"first_arg": "cls"}, "fallback": "builtins.function", "implicit": false, "is_ellipsis_args": false, "name": "Name of DateError", "ret_type": "builtins.str", "variables": []}}}}, "UNKNOWN": {".class": "SymbolTableNode", "kind": "Mdef", "node": {".class": "Var", "flags": ["is_initialized_in_class", "is_ready"], "fullname": "google.ads.google_ads.v2.proto.errors.date_error_pb2.DateErrorEnum.DateError.UNKNOWN", "name": "UNKNOWN", "type": {".class": "LiteralType", "fallback": "builtins.int", "value": 1}}}, "UNSPECIFIED": {".class": "SymbolTableNode", "kind": "Mdef", "node": {".class": "Var", "flags": ["is_initialized_in_class", "is_ready"], "fullname": "google.ads.google_ads.v2.proto.errors.date_error_pb2.DateErrorEnum.DateError.UNSPECIFIED", "name": "UNSPECIFIED", "type": {".class": "LiteralType", "fallback": "builtins.int", "value": 0}}}, "Value": {".class": "SymbolTableNode", "kind": "Mdef", "node": {".class": "Decorator", "func": {".class": "FuncDef", "arg_kinds": [0, 0], "arg_names": ["cls", "name"], "flags": ["is_class", "is_decorated"], "fullname": "google.ads.google_ads.v2.proto.errors.date_error_pb2.DateErrorEnum.DateError.Value", "name": "Value", "type": {".class": "CallableType", "arg_kinds": [0, 0], "arg_names": ["cls", "name"], "arg_types": [{".class": "TypeType", "item": "google.ads.google_ads.v2.proto.errors.date_error_pb2.DateErrorEnum.DateError"}, {".class": "UnionType", "items": [{".class": "LiteralType", "fallback": "builtins.str", "value": "UNSPECIFIED"}, {".class": "LiteralType", "fallback": "builtins.str", "value": "UNKNOWN"}, {".class": "LiteralType", "fallback": "builtins.str", "value": "INVALID_FIELD_VALUES_IN_DATE"}, {".class": "LiteralType", "fallback": "builtins.str", "value": "INVALID_FIELD_VALUES_IN_DATE_TIME"}, {".class": "LiteralType", "fallback": "builtins.str", "value": "INVALID_STRING_DATE"}, {".class": "LiteralType", "fallback": "builtins.str", "value": "INVALID_STRING_DATE_TIME_MICROS"}, {".class": "LiteralType", "fallback": "builtins.str", "value": "INVALID_STRING_DATE_TIME_SECONDS"}, {".class": "LiteralType", "fallback": "builtins.str", "value": "INVALID_STRING_DATE_TIME_SECONDS_WITH_OFFSET"}, {".class": "LiteralType", "fallback": "builtins.str", "value": "EARLIER_THAN_MINIMUM_DATE"}, {".class": "LiteralType", "fallback": "builtins.str", "value": "LATER_THAN_MAXIMUM_DATE"}, {".class": "LiteralType", "fallback": "builtins.str", "value": "DATE_RANGE_MINIMUM_DATE_LATER_THAN_MAXIMUM_DATE"}, {".class": "LiteralType", "fallback": "builtins.str", "value": "DATE_RANGE_MINIMUM_AND_MAXIMUM_DATES_BOTH_NULL"}]}], "bound_args": [], "def_extras": {"first_arg": "cls"}, "fallback": "builtins.function", "implicit": false, "is_ellipsis_args": false, "name": "Value of DateError", "ret_type": {".class": "UnionType", "items": [{".class": "LiteralType", "fallback": "builtins.int", "value": 0}, {".class": "LiteralType", "fallback": "builtins.int", "value": 1}, {".class": "LiteralType", "fallback": "builtins.int", "value": 2}, {".class": "LiteralType", "fallback": "builtins.int", "value": 3}, {".class": "LiteralType", "fallback": "builtins.int", "value": 4}, {".class": "LiteralType", "fallback": "builtins.int", "value": 6}, {".class": "LiteralType", "fallback": "builtins.int", "value": 11}, {".class": "LiteralType", "fallback": "builtins.int", "value": 12}, {".class": "LiteralType", "fallback": "builtins.int", "value": 7}, {".class": "LiteralType", "fallback": "builtins.int", "value": 8}, {".class": "LiteralType", "fallback": "builtins.int", "value": 9}, {".class": "LiteralType", "fallback": "builtins.int", "value": 10}]}, "variables": []}}, "is_overload": false, "var": {".class": "Var", "flags": ["is_initialized_in_class", "is_classmethod", "is_ready"], "fullname": null, "name": "Value", "type": {".class": "CallableType", "arg_kinds": [0, 0], "arg_names": ["cls", "name"], "arg_types": [{".class": "TypeType", "item": "google.ads.google_ads.v2.proto.errors.date_error_pb2.DateErrorEnum.DateError"}, {".class": "UnionType", "items": [{".class": "LiteralType", "fallback": "builtins.str", "value": "UNSPECIFIED"}, {".class": "LiteralType", "fallback": "builtins.str", "value": "UNKNOWN"}, {".class": "LiteralType", "fallback": "builtins.str", "value": "INVALID_FIELD_VALUES_IN_DATE"}, {".class": "LiteralType", "fallback": "builtins.str", "value": "INVALID_FIELD_VALUES_IN_DATE_TIME"}, {".class": "LiteralType", "fallback": "builtins.str", "value": "INVALID_STRING_DATE"}, {".class": "LiteralType", "fallback": "builtins.str", "value": "INVALID_STRING_DATE_TIME_MICROS"}, {".class": "LiteralType", "fallback": "builtins.str", "value": "INVALID_STRING_DATE_TIME_SECONDS"}, {".class": "LiteralType", "fallback": "builtins.str", "value": "INVALID_STRING_DATE_TIME_SECONDS_WITH_OFFSET"}, {".class": "LiteralType", "fallback": "builtins.str", "value": "EARLIER_THAN_MINIMUM_DATE"}, {".class": "LiteralType", "fallback": "builtins.str", "value": "LATER_THAN_MAXIMUM_DATE"}, {".class": "LiteralType", "fallback": "builtins.str", "value": "DATE_RANGE_MINIMUM_DATE_LATER_THAN_MAXIMUM_DATE"}, {".class": "LiteralType", "fallback": "builtins.str", "value": "DATE_RANGE_MINIMUM_AND_MAXIMUM_DATES_BOTH_NULL"}]}], "bound_args": [], "def_extras": {"first_arg": "cls"}, "fallback": "builtins.function", "implicit": false, "is_ellipsis_args": false, "name": "Value of DateError", "ret_type": {".class": "UnionType", "items": [{".class": "LiteralType", "fallback": "builtins.int", "value": 0}, {".class": "LiteralType", "fallback": "builtins.int", "value": 1}, {".class": "LiteralType", "fallback": "builtins.int", "value": 2}, {".class": "LiteralType", "fallback": "builtins.int", "value": 3}, {".class": "LiteralType", "fallback": "builtins.int", "value": 4}, {".class": "LiteralType", "fallback": "builtins.int", "value": 6}, {".class": "LiteralType", "fallback": "builtins.int", "value": 11}, {".class": "LiteralType", "fallback": "builtins.int", "value": 12}, {".class": "LiteralType", "fallback": "builtins.int", "value": 7}, {".class": "LiteralType", "fallback": "builtins.int", "value": 8}, {".class": "LiteralType", "fallback": "builtins.int", "value": 9}, {".class": "LiteralType", "fallback": "builtins.int", "value": 10}]}, "variables": []}}}}, "items": {".class": "SymbolTableNode", "kind": "Mdef", "node": {".class": "Decorator", "func": {".class": "FuncDef", "arg_kinds": [0], "arg_names": ["cls"], "flags": ["is_class", "is_decorated"], "fullname": "google.ads.google_ads.v2.proto.errors.date_error_pb2.DateErrorEnum.DateError.items", "name": "items", "type": {".class": "CallableType", "arg_kinds": [0], "arg_names": ["cls"], "arg_types": [{".class": "TypeType", "item": "google.ads.google_ads.v2.proto.errors.date_error_pb2.DateErrorEnum.DateError"}], "bound_args": [], "def_extras": {"first_arg": "cls"}, "fallback": "builtins.function", "implicit": false, "is_ellipsis_args": false, "name": "items of DateError", "ret_type": {".class": "Instance", "args": [{".class": "TupleType", "implicit": false, "items": [{".class": "UnionType", "items": [{".class": "LiteralType", "fallback": "builtins.str", "value": "UNSPECIFIED"}, {".class": "LiteralType", "fallback": "builtins.str", "value": "UNKNOWN"}, {".class": "LiteralType", "fallback": "builtins.str", "value": "INVALID_FIELD_VALUES_IN_DATE"}, {".class": "LiteralType", "fallback": "builtins.str", "value": "INVALID_FIELD_VALUES_IN_DATE_TIME"}, {".class": "LiteralType", "fallback": "builtins.str", "value": "INVALID_STRING_DATE"}, {".class": "LiteralType", "fallback": "builtins.str", "value": "INVALID_STRING_DATE_TIME_MICROS"}, {".class": "LiteralType", "fallback": "builtins.str", "value": "INVALID_STRING_DATE_TIME_SECONDS"}, {".class": "LiteralType", "fallback": "builtins.str", "value": "INVALID_STRING_DATE_TIME_SECONDS_WITH_OFFSET"}, {".class": "LiteralType", "fallback": "builtins.str", "value": "EARLIER_THAN_MINIMUM_DATE"}, {".class": "LiteralType", "fallback": "builtins.str", "value": "LATER_THAN_MAXIMUM_DATE"}, {".class": "LiteralType", "fallback": "builtins.str", "value": "DATE_RANGE_MINIMUM_DATE_LATER_THAN_MAXIMUM_DATE"}, {".class": "LiteralType", "fallback": "builtins.str", "value": "DATE_RANGE_MINIMUM_AND_MAXIMUM_DATES_BOTH_NULL"}]}, {".class": "UnionType", "items": [{".class": "LiteralType", "fallback": "builtins.int", "value": 0}, {".class": "LiteralType", "fallback": "builtins.int", "value": 1}, {".class": "LiteralType", "fallback": "builtins.int", "value": 2}, {".class": "LiteralType", "fallback": "builtins.int", "value": 3}, {".class": "LiteralType", "fallback": "builtins.int", "value": 4}, {".class": "LiteralType", "fallback": "builtins.int", "value": 6}, {".class": "LiteralType", "fallback": "builtins.int", "value": 11}, {".class": "LiteralType", "fallback": "builtins.int", "value": 12}, {".class": "LiteralType", "fallback": "builtins.int", "value": 7}, {".class": "LiteralType", "fallback": "builtins.int", "value": 8}, {".class": "LiteralType", "fallback": "builtins.int", "value": 9}, {".class": "LiteralType", "fallback": "builtins.int", "value": 10}]}], "partial_fallback": {".class": "Instance", "args": [{".class": "AnyType", "missing_import_name": null, "source_any": null, "type_of_any": 6}], "type_ref": "builtins.tuple"}}], "type_ref": "builtins.list"}, "variables": []}}, "is_overload": false, "var": {".class": "Var", "flags": ["is_initialized_in_class", "is_classmethod", "is_ready"], "fullname": null, "name": "items", "type": {".class": "CallableType", "arg_kinds": [0], "arg_names": ["cls"], "arg_types": [{".class": "TypeType", "item": "google.ads.google_ads.v2.proto.errors.date_error_pb2.DateErrorEnum.DateError"}], "bound_args": [], "def_extras": {"first_arg": "cls"}, "fallback": "builtins.function", "implicit": false, "is_ellipsis_args": false, "name": "items of DateError", "ret_type": {".class": "Instance", "args": [{".class": "TupleType", "implicit": false, "items": [{".class": "UnionType", "items": [{".class": "LiteralType", "fallback": "builtins.str", "value": "UNSPECIFIED"}, {".class": "LiteralType", "fallback": "builtins.str", "value": "UNKNOWN"}, {".class": "LiteralType", "fallback": "builtins.str", "value": "INVALID_FIELD_VALUES_IN_DATE"}, {".class": "LiteralType", "fallback": "builtins.str", "value": "INVALID_FIELD_VALUES_IN_DATE_TIME"}, {".class": "LiteralType", "fallback": "builtins.str", "value": "INVALID_STRING_DATE"}, {".class": "LiteralType", "fallback": "builtins.str", "value": "INVALID_STRING_DATE_TIME_MICROS"}, {".class": "LiteralType", "fallback": "builtins.str", "value": "INVALID_STRING_DATE_TIME_SECONDS"}, {".class": "LiteralType", "fallback": "builtins.str", "value": "INVALID_STRING_DATE_TIME_SECONDS_WITH_OFFSET"}, {".class": "LiteralType", "fallback": "builtins.str", "value": "EARLIER_THAN_MINIMUM_DATE"}, {".class": "LiteralType", "fallback": "builtins.str", "value": "LATER_THAN_MAXIMUM_DATE"}, {".class": "LiteralType", "fallback": "builtins.str", "value": "DATE_RANGE_MINIMUM_DATE_LATER_THAN_MAXIMUM_DATE"}, {".class": "LiteralType", "fallback": "builtins.str", "value": "DATE_RANGE_MINIMUM_AND_MAXIMUM_DATES_BOTH_NULL"}]}, {".class": "UnionType", "items": [{".class": "LiteralType", "fallback": "builtins.int", "value": 0}, {".class": "LiteralType", "fallback": "builtins.int", "value": 1}, {".class": "LiteralType", "fallback": "builtins.int", "value": 2}, {".class": "LiteralType", "fallback": "builtins.int", "value": 3}, {".class": "LiteralType", "fallback": "builtins.int", "value": 4}, {".class": "LiteralType", "fallback": "builtins.int", "value": 6}, {".class": "LiteralType", "fallback": "builtins.int", "value": 11}, {".class": "LiteralType", "fallback": "builtins.int", "value": 12}, {".class": "LiteralType", "fallback": "builtins.int", "value": 7}, {".class": "LiteralType", "fallback": "builtins.int", "value": 8}, {".class": "LiteralType", "fallback": "builtins.int", "value": 9}, {".class": "LiteralType", "fallback": "builtins.int", "value": 10}]}], "partial_fallback": {".class": "Instance", "args": [{".class": "AnyType", "missing_import_name": null, "source_any": null, "type_of_any": 6}], "type_ref": "builtins.tuple"}}], "type_ref": "builtins.list"}, "variables": []}}}}, "keys": {".class": "SymbolTableNode", "kind": "Mdef", "node": {".class": "Decorator", "func": {".class": "FuncDef", "arg_kinds": [0], "arg_names": ["cls"], "flags": ["is_class", "is_decorated"], "fullname": "google.ads.google_ads.v2.proto.errors.date_error_pb2.DateErrorEnum.DateError.keys", "name": "keys", "type": {".class": "CallableType", "arg_kinds": [0], "arg_names": ["cls"], "arg_types": [{".class": "TypeType", "item": "google.ads.google_ads.v2.proto.errors.date_error_pb2.DateErrorEnum.DateError"}], "bound_args": [], "def_extras": {"first_arg": "cls"}, "fallback": "builtins.function", "implicit": false, "is_ellipsis_args": false, "name": "keys of DateError", "ret_type": {".class": "Instance", "args": [{".class": "UnionType", "items": [{".class": "LiteralType", "fallback": "builtins.str", "value": "UNSPECIFIED"}, {".class": "LiteralType", "fallback": "builtins.str", "value": "UNKNOWN"}, {".class": "LiteralType", "fallback": "builtins.str", "value": "INVALID_FIELD_VALUES_IN_DATE"}, {".class": "LiteralType", "fallback": "builtins.str", "value": "INVALID_FIELD_VALUES_IN_DATE_TIME"}, {".class": "LiteralType", "fallback": "builtins.str", "value": "INVALID_STRING_DATE"}, {".class": "LiteralType", "fallback": "builtins.str", "value": "INVALID_STRING_DATE_TIME_MICROS"}, {".class": "LiteralType", "fallback": "builtins.str", "value": "INVALID_STRING_DATE_TIME_SECONDS"}, {".class": "LiteralType", "fallback": "builtins.str", "value": "INVALID_STRING_DATE_TIME_SECONDS_WITH_OFFSET"}, {".class": "LiteralType", "fallback": "builtins.str", "value": "EARLIER_THAN_MINIMUM_DATE"}, {".class": "LiteralType", "fallback": "builtins.str", "value": "LATER_THAN_MAXIMUM_DATE"}, {".class": "LiteralType", "fallback": "builtins.str", "value": "DATE_RANGE_MINIMUM_DATE_LATER_THAN_MAXIMUM_DATE"}, {".class": "LiteralType", "fallback": "builtins.str", "value": "DATE_RANGE_MINIMUM_AND_MAXIMUM_DATES_BOTH_NULL"}]}], "type_ref": "builtins.list"}, "variables": []}}, "is_overload": false, "var": {".class": "Var", "flags": ["is_initialized_in_class", "is_classmethod", "is_ready"], "fullname": null, "name": "keys", "type": {".class": "CallableType", "arg_kinds": [0], "arg_names": ["cls"], "arg_types": [{".class": "TypeType", "item": "google.ads.google_ads.v2.proto.errors.date_error_pb2.DateErrorEnum.DateError"}], "bound_args": [], "def_extras": {"first_arg": "cls"}, "fallback": "builtins.function", "implicit": false, "is_ellipsis_args": false, "name": "keys of DateError", "ret_type": {".class": "Instance", "args": [{".class": "UnionType", "items": [{".class": "LiteralType", "fallback": "builtins.str", "value": "UNSPECIFIED"}, {".class": "LiteralType", "fallback": "builtins.str", "value": "UNKNOWN"}, {".class": "LiteralType", "fallback": "builtins.str", "value": "INVALID_FIELD_VALUES_IN_DATE"}, {".class": "LiteralType", "fallback": "builtins.str", "value": "INVALID_FIELD_VALUES_IN_DATE_TIME"}, {".class": "LiteralType", "fallback": "builtins.str", "value": "INVALID_STRING_DATE"}, {".class": "LiteralType", "fallback": "builtins.str", "value": "INVALID_STRING_DATE_TIME_MICROS"}, {".class": "LiteralType", "fallback": "builtins.str", "value": "INVALID_STRING_DATE_TIME_SECONDS"}, {".class": "LiteralType", "fallback": "builtins.str", "value": "INVALID_STRING_DATE_TIME_SECONDS_WITH_OFFSET"}, {".class": "LiteralType", "fallback": "builtins.str", "value": "EARLIER_THAN_MINIMUM_DATE"}, {".class": "LiteralType", "fallback": "builtins.str", "value": "LATER_THAN_MAXIMUM_DATE"}, {".class": "LiteralType", "fallback": "builtins.str", "value": "DATE_RANGE_MINIMUM_DATE_LATER_THAN_MAXIMUM_DATE"}, {".class": "LiteralType", "fallback": "builtins.str", "value": "DATE_RANGE_MINIMUM_AND_MAXIMUM_DATES_BOTH_NULL"}]}], "type_ref": "builtins.list"}, "variables": []}}}}, "values": {".class": "SymbolTableNode", "kind": "Mdef", "node": {".class": "Decorator", "func": {".class": "FuncDef", "arg_kinds": [0], "arg_names": ["cls"], "flags": ["is_class", "is_decorated"], "fullname": "google.ads.google_ads.v2.proto.errors.date_error_pb2.DateErrorEnum.DateError.values", "name": "values", "type": {".class": "CallableType", "arg_kinds": [0], "arg_names": ["cls"], "arg_types": [{".class": "TypeType", "item": "google.ads.google_ads.v2.proto.errors.date_error_pb2.DateErrorEnum.DateError"}], "bound_args": [], "def_extras": {"first_arg": "cls"}, "fallback": "builtins.function", "implicit": false, "is_ellipsis_args": false, "name": "values of DateError", "ret_type": {".class": "Instance", "args": [{".class": "UnionType", "items": [{".class": "LiteralType", "fallback": "builtins.int", "value": 0}, {".class": "LiteralType", "fallback": "builtins.int", "value": 1}, {".class": "LiteralType", "fallback": "builtins.int", "value": 2}, {".class": "LiteralType", "fallback": "builtins.int", "value": 3}, {".class": "LiteralType", "fallback": "builtins.int", "value": 4}, {".class": "LiteralType", "fallback": "builtins.int", "value": 6}, {".class": "LiteralType", "fallback": "builtins.int", "value": 11}, {".class": "LiteralType", "fallback": "builtins.int", "value": 12}, {".class": "LiteralType", "fallback": "builtins.int", "value": 7}, {".class": "LiteralType", "fallback": "builtins.int", "value": 8}, {".class": "LiteralType", "fallback": "builtins.int", "value": 9}, {".class": "LiteralType", "fallback": "builtins.int", "value": 10}]}], "type_ref": "builtins.list"}, "variables": []}}, "is_overload": false, "var": {".class": "Var", "flags": ["is_initialized_in_class", "is_classmethod", "is_ready"], "fullname": null, "name": "values", "type": {".class": "CallableType", "arg_kinds": [0], "arg_names": ["cls"], "arg_types": [{".class": "TypeType", "item": "google.ads.google_ads.v2.proto.errors.date_error_pb2.DateErrorEnum.DateError"}], "bound_args": [], "def_extras": {"first_arg": "cls"}, "fallback": "builtins.function", "implicit": false, "is_ellipsis_args": false, "name": "values of DateError", "ret_type": {".class": "Instance", "args": [{".class": "UnionType", "items": [{".class": "LiteralType", "fallback": "builtins.int", "value": 0}, {".class": "LiteralType", "fallback": "builtins.int", "value": 1}, {".class": "LiteralType", "fallback": "builtins.int", "value": 2}, {".class": "LiteralType", "fallback": "builtins.int", "value": 3}, {".class": "LiteralType", "fallback": "builtins.int", "value": 4}, {".class": "LiteralType", "fallback": "builtins.int", "value": 6}, {".class": "LiteralType", "fallback": "builtins.int", "value": 11}, {".class": "LiteralType", "fallback": "builtins.int", "value": 12}, {".class": "LiteralType", "fallback": "builtins.int", "value": 7}, {".class": "LiteralType", "fallback": "builtins.int", "value": 8}, {".class": "LiteralType", "fallback": "builtins.int", "value": 9}, {".class": "LiteralType", "fallback": "builtins.int", "value": 10}]}], "type_ref": "builtins.list"}, "variables": []}}}}}, "tuple_type": null, "type_vars": [], "typeddict_type": null}}, "EARLIER_THAN_MINIMUM_DATE": {".class": "SymbolTableNode", "kind": "Mdef", "node": {".class": "Var", "flags": ["is_initialized_in_class", "is_ready"], "fullname": "google.ads.google_ads.v2.proto.errors.date_error_pb2.DateErrorEnum.EARLIER_THAN_MINIMUM_DATE", "name": "EARLIER_THAN_MINIMUM_DATE", "type": {".class": "LiteralType", "fallback": "builtins.int", "value": 7}}}, "FromString": {".class": "SymbolTableNode", "kind": "Mdef", "node": {".class": "Decorator", "func": {".class": "FuncDef", "arg_kinds": [0, 0], "arg_names": ["cls", "s"], "flags": ["is_class", "is_decorated"], "fullname": "google.ads.google_ads.v2.proto.errors.date_error_pb2.DateErrorEnum.FromString", "name": "FromString", "type": {".class": "CallableType", "arg_kinds": [0, 0], "arg_names": ["cls", "s"], "arg_types": [{".class": "TypeType", "item": "google.ads.google_ads.v2.proto.errors.date_error_pb2.DateErrorEnum"}, "builtins.bytes"], "bound_args": [], "def_extras": {"first_arg": "cls"}, "fallback": "builtins.function", "implicit": false, "is_ellipsis_args": false, "name": "FromString of DateErrorEnum", "ret_type": "google.ads.google_ads.v2.proto.errors.date_error_pb2.DateErrorEnum", "variables": []}}, "is_overload": false, "var": {".class": "Var", "flags": ["is_initialized_in_class", "is_classmethod", "is_ready"], "fullname": null, "name": "FromString", "type": {".class": "CallableType", "arg_kinds": [0, 0], "arg_names": ["cls", "s"], "arg_types": [{".class": "TypeType", "item": "google.ads.google_ads.v2.proto.errors.date_error_pb2.DateErrorEnum"}, "builtins.bytes"], "bound_args": [], "def_extras": {"first_arg": "cls"}, "fallback": "builtins.function", "implicit": false, "is_ellipsis_args": false, "name": "FromString of DateErrorEnum", "ret_type": "google.ads.google_ads.v2.proto.errors.date_error_pb2.DateErrorEnum", "variables": []}}}}, "INVALID_FIELD_VALUES_IN_DATE": {".class": "SymbolTableNode", "kind": "Mdef", "node": {".class": "Var", "flags": ["is_initialized_in_class", "is_ready"], "fullname": "google.ads.google_ads.v2.proto.errors.date_error_pb2.DateErrorEnum.INVALID_FIELD_VALUES_IN_DATE", "name": "INVALID_FIELD_VALUES_IN_DATE", "type": {".class": "LiteralType", "fallback": "builtins.int", "value": 2}}}, "INVALID_FIELD_VALUES_IN_DATE_TIME": {".class": "SymbolTableNode", "kind": "Mdef", "node": {".class": "Var", "flags": ["is_initialized_in_class", "is_ready"], "fullname": "google.ads.google_ads.v2.proto.errors.date_error_pb2.DateErrorEnum.INVALID_FIELD_VALUES_IN_DATE_TIME", "name": "INVALID_FIELD_VALUES_IN_DATE_TIME", "type": {".class": "LiteralType", "fallback": "builtins.int", "value": 3}}}, "INVALID_STRING_DATE": {".class": "SymbolTableNode", "kind": "Mdef", "node": {".class": "Var", "flags": ["is_initialized_in_class", "is_ready"], "fullname": "google.ads.google_ads.v2.proto.errors.date_error_pb2.DateErrorEnum.INVALID_STRING_DATE", "name": "INVALID_STRING_DATE", "type": {".class": "LiteralType", "fallback": "builtins.int", "value": 4}}}, "INVALID_STRING_DATE_TIME_MICROS": {".class": "SymbolTableNode", "kind": "Mdef", "node": {".class": "Var", "flags": ["is_initialized_in_class", "is_ready"], "fullname": "google.ads.google_ads.v2.proto.errors.date_error_pb2.DateErrorEnum.INVALID_STRING_DATE_TIME_MICROS", "name": "INVALID_STRING_DATE_TIME_MICROS", "type": {".class": "LiteralType", "fallback": "builtins.int", "value": 6}}}, "INVALID_STRING_DATE_TIME_SECONDS": {".class": "SymbolTableNode", "kind": "Mdef", "node": {".class": "Var", "flags": ["is_initialized_in_class", "is_ready"], "fullname": "google.ads.google_ads.v2.proto.errors.date_error_pb2.DateErrorEnum.INVALID_STRING_DATE_TIME_SECONDS", "name": "INVALID_STRING_DATE_TIME_SECONDS", "type": {".class": "LiteralType", "fallback": "builtins.int", "value": 11}}}, "INVALID_STRING_DATE_TIME_SECONDS_WITH_OFFSET": {".class": "SymbolTableNode", "kind": "Mdef", "node": {".class": "Var", "flags": ["is_initialized_in_class", "is_ready"], "fullname": "google.ads.google_ads.v2.proto.errors.date_error_pb2.DateErrorEnum.INVALID_STRING_DATE_TIME_SECONDS_WITH_OFFSET", "name": "INVALID_STRING_DATE_TIME_SECONDS_WITH_OFFSET", "type": {".class": "LiteralType", "fallback": "builtins.int", "value": 12}}}, "LATER_THAN_MAXIMUM_DATE": {".class": "SymbolTableNode", "kind": "Mdef", "node": {".class": "Var", "flags": ["is_initialized_in_class", "is_ready"], "fullname": "google.ads.google_ads.v2.proto.errors.date_error_pb2.DateErrorEnum.LATER_THAN_MAXIMUM_DATE", "name": "LATER_THAN_MAXIMUM_DATE", "type": {".class": "LiteralType", "fallback": "builtins.int", "value": 8}}}, "MergeFrom": {".class": "SymbolTableNode", "kind": "Mdef", "node": {".class": "FuncDef", "arg_kinds": [0, 0], "arg_names": ["self", "other_msg"], "flags": [], "fullname": "google.ads.google_ads.v2.proto.errors.date_error_pb2.DateErrorEnum.MergeFrom", "name": "MergeFrom", "type": {".class": "CallableType", "arg_kinds": [0, 0], "arg_names": ["self", "other_msg"], "arg_types": ["google.ads.google_ads.v2.proto.errors.date_error_pb2.DateErrorEnum", "google.protobuf.message.Message"], "bound_args": [], "def_extras": {"first_arg": "self"}, "fallback": "builtins.function", "implicit": false, "is_ellipsis_args": false, "name": "MergeFrom of DateErrorEnum", "ret_type": {".class": "NoneType"}, "variables": []}}}, "UNKNOWN": {".class": "SymbolTableNode", "kind": "Mdef", "node": {".class": "Var", "flags": ["is_initialized_in_class", "is_ready"], "fullname": "google.ads.google_ads.v2.proto.errors.date_error_pb2.DateErrorEnum.UNKNOWN", "name": "UNKNOWN", "type": {".class": "LiteralType", "fallback": "builtins.int", "value": 1}}}, "UNSPECIFIED": {".class": "SymbolTableNode", "kind": "Mdef", "node": {".class": "Var", "flags": ["is_initialized_in_class", "is_ready"], "fullname": "google.ads.google_ads.v2.proto.errors.date_error_pb2.DateErrorEnum.UNSPECIFIED", "name": "UNSPECIFIED", "type": {".class": "LiteralType", "fallback": "builtins.int", "value": 0}}}, "__init__": {".class": "SymbolTableNode", "kind": "Mdef", "node": {".class": "FuncDef", "arg_kinds": [0], "arg_names": ["self"], "flags": [], "fullname": "google.ads.google_ads.v2.proto.errors.date_error_pb2.DateErrorEnum.__init__", "name": "__init__", "type": {".class": "CallableType", "arg_kinds": [0], "arg_names": ["self"], "arg_types": ["google.ads.google_ads.v2.proto.errors.date_error_pb2.DateErrorEnum"], "bound_args": [], "def_extras": {"first_arg": "self"}, "fallback": "builtins.function", "implicit": false, "is_ellipsis_args": false, "name": "__init__ of DateErrorEnum", "ret_type": {".class": "NoneType"}, "variables": []}}}}, "tuple_type": null, "type_vars": [], "typeddict_type": null}}, "__doc__": {".class": "SymbolTableNode", "kind": "Gdef", "node": {".class": "Var", "flags": ["is_ready"], "fullname": "google.ads.google_ads.v2.proto.errors.date_error_pb2.__doc__", "name": "__doc__", "type": "builtins.str"}}, "__file__": {".class": "SymbolTableNode", "kind": "Gdef", "node": {".class": "Var", "flags": ["is_ready"], "fullname": "google.ads.google_ads.v2.proto.errors.date_error_pb2.__file__", "name": "__file__", "type": "builtins.str"}}, "__name__": {".class": "SymbolTableNode", "kind": "Gdef", "node": {".class": "Var", "flags": ["is_ready"], "fullname": "google.ads.google_ads.v2.proto.errors.date_error_pb2.__name__", "name": "__name__", "type": "builtins.str"}}, "__package__": {".class": "SymbolTableNode", "kind": "Gdef", "node": {".class": "Var", "flags": ["is_ready"], "fullname": "google.ads.google_ads.v2.proto.errors.date_error_pb2.__package__", "name": "__package__", "type": "builtins.str"}}, "google___protobuf___descriptor___EnumDescriptor": {".class": "SymbolTableNode", "cross_ref": "google.protobuf.descriptor.EnumDescriptor", "kind": "Gdef"}, "google___protobuf___message___Message": {".class": "SymbolTableNode", "cross_ref": "google.protobuf.message.Message", "kind": "Gdef"}, "sys": {".class": "SymbolTableNode", "cross_ref": "sys", "kind": "Gdef", "module_hidden": true, "module_public": false}, "typing___List": {".class": "SymbolTableNode", "cross_ref": "typing.List", "kind": "Gdef"}, "typing___Tuple": {".class": "SymbolTableNode", "cross_ref": "typing.Tuple", "kind": "Gdef"}, "typing___Union": {".class": "SymbolTableNode", "cross_ref": "typing.Union", "kind": "Gdef"}, "typing_extensions___Literal": {".class": "SymbolTableNode", "cross_ref": "typing_extensions.Literal", "kind": "Gdef"}}, "path": "/home/henbruas/.local/share/virtualenvs/google-ads-stubs-8D4ODehI/lib/python3.7/site-packages/google-stubs/ads/google_ads/v2/proto/errors/date_error_pb2.pyi"}